tex2docx/__init__.py
tex2docx/__main__.py
tex2docx/cli.py
tex2docx/config.py
tex2docx/constants.py
tex2docx/converter.py
tex2docx/default_temp.docx
tex2docx/exceptions.py
tex2docx/file_manager.py
tex2docx/ieee.csl
tex2docx/modifier.py
tex2docx/parser.py
tex2docx/resolve_equation_labels.lua
tex2docx/subfile.py
tex2docx/tex2docx.py
tex2docx/tex2docx_legacy.py
tex2docx/utils.py
tex2docx-1.3.0.dist-info/LICENSE
tex2docx-1.3.0.dist-info/METADATA
tex2docx-1.3.0.dist-info/WHEEL
tex2docx-1.3.0.dist-info/entry_points.txt
tex2docx-1.3.0.dist-info/top_level.txt
tex2docx-1.3.0.dist-info/RECORD
