Metadata-Version: 2.1
Name: tex2docx
Version: 1.3.0
Summary: A project to convert LaTeX to DOCX
Author-email: Mingzefei <huagb@qq.com>
Classifier: Development Status :: 4 - Beta
Classifier: Programming Language :: Python :: 3
Classifier: License :: OSI Approved :: MIT License
Classifier: Operating System :: OS Independent
Requires-Python: >=3.8
License-File: LICENSE
Requires-Dist: regex
Requires-Dist: tqdm
Requires-Dist: typer
Provides-Extra: dev
Requires-Dist: ruff; extra == "dev"
Requires-Dist: mypy; extra == "dev"
Requires-Dist: pytest; extra == "dev"
